Metadata-Version: 2.1
Name: textoria
Version: 0.0.1
Summary: Textoria API Client for Python
Author: lor3m
Author-email: hiddenlorem@pm.me
License: MIT License
Project-URL: Source Code, https://github.com/textoria/textoria-python
Classifier: Programming Language :: Python
Classifier: Programming Language :: Python :: 3
Classifier: Programming Language :: Python :: 3.10
Classifier: Programming Language :: Python :: 3.11
Classifier: Intended Audience :: Developers
Classifier: Operating System :: OS Independent
Classifier: Topic :: Software Development :: Libraries :: Python Modules
Classifier: Topic :: Internet
Requires-Python: >=3.8
License-File: LICENSE
